anynotify.py
anynotify-0.0.1.dist-info/METADATA
anynotify-0.0.1.dist-info/WHEEL
anynotify-0.0.1.dist-info/top_level.txt
anynotify-0.0.1.dist-info/RECORD
